weasl/__init__.py
weasl/__version__.py
weasl/api.py
weasl/exceptions.py
weasl/user.py
weasl/integrations/__init__.py
weasl/integrations/flask.py
weasl_sdk-0.0.2.dist-info/METADATA
weasl_sdk-0.0.2.dist-info/WHEEL
weasl_sdk-0.0.2.dist-info/top_level.txt
weasl_sdk-0.0.2.dist-info/RECORD
