Metadata-Version: 2.1
Name: weasl-sdk
Version: 0.0.2
Summary: Python SDK for weasl.in
Home-page: http://docs.weasl.in
Author: Ryan Baker
License: Apache 2.0
Platform: UNKNOWN
Classifier: Development Status :: 5 - Production/Stable
Classifier: Intended Audience :: Developers
Classifier: Natural Language :: English
Classifier: License :: OSI Approved :: Apache Software License
Classifier: Programming Language :: Python
Classifier: Programming Language :: Python :: 2
Classifier: Programming Language :: Python :: 2.7
Classifier: Programming Language :: Python :: 3
Classifier: Programming Language :: Python :: 3.4
Classifier: Programming Language :: Python :: 3.5
Classifier: Programming Language :: Python :: 3.6
Classifier: Programming Language :: Python :: 3.7
Classifier: Programming Language :: Python :: Implementation :: CPython
Classifier: Programming Language :: Python :: Implementation :: PyPy
Requires-Python: >=2.7
Requires-Dist: requests (<3.0.0,>=2.0.0)
Provides-Extra: flask
Requires-Dist: flask (>=0.8) ; extra == 'flask'
Requires-Dist: blinker (>=1.1) ; extra == 'flask'
